setup.cfg
setup.py
mettle_protocol/__init__.py
mettle_protocol/messages.py
mettle_protocol/service.py
mettle_protocol.egg-info/PKG-INFO
mettle_protocol.egg-info/SOURCES.txt
mettle_protocol.egg-info/dependency_links.txt
mettle_protocol.egg-info/requires.txt
mettle_protocol.egg-info/top_level.txt