Metadata-Version: 1.0
Name: mettle-protocol
Version: 1.2.1
Summary: A robust framework for scheduling and executing ETL jobs.
Home-page: UNKNOWN
Author: Y Team
Author-email: alejandro.rivera@yougov.com, fernando.gutierrez@yougov.com, brent.tubbs@gmail.com
License: UNKNOWN
Platform: UNKNOWN
